README.md
getquote.py
setup.py
getquote.egg-info/PKG-INFO
getquote.egg-info/SOURCES.txt
getquote.egg-info/dependency_links.txt
getquote.egg-info/entry_points.txt
getquote.egg-info/top_level.txt