Metadata-Version: 2.1
Name: getquote
Version: 1.2.0
Summary: A ledger-cli getquote implementation using free IEX Cloud API
Home-page: https://github.com/jeanralphaviles/getquote
Author: Jean-Ralph Aviles
Author-email: jeanralph.aviles@gmail.com
License: MIT
Keywords: ledger-cli personal finance stocks
Platform: UNKNOWN
